adafruit_bno055.py
adafruit_circuitpython_bno055-5.4.19.dist-info/licenses/LICENSE
adafruit_circuitpython_bno055-5.4.19.dist-info/METADATA
adafruit_circuitpython_bno055-5.4.19.dist-info/WHEEL
adafruit_circuitpython_bno055-5.4.19.dist-info/top_level.txt
adafruit_circuitpython_bno055-5.4.19.dist-info/RECORD
